patmlkit/__init__.py
patmlkit/coco.py
patmlkit/image.py
patmlkit/json.py
patmlkit-0.1.3.post2.dist-info/WHEEL
patmlkit-0.1.3.post2.dist-info/METADATA
patmlkit-0.1.3.post2.dist-info/RECORD
