Metadata-Version: 2.1
Name: patmlkit
Version: 0.1.3.post2
Summary: Pain and tears ML kit - library created to support my journey via PHD
Author: Michal Karol
Author-email: michal.p.karol@gmail.com
Requires-Python: >=3.10,<4.0
Classifier: Programming Language :: Python :: 3
Classifier: Programming Language :: Python :: 3.10
Classifier: Programming Language :: Python :: 3.11
Requires-Dist: imagesize (>=1.4.1,<2.0.0)
Requires-Dist: numpy (>=1.23.3,<2.0.0)
Requires-Dist: opencv-python (>=4.6.0.66,<5.0.0.0)
Requires-Dist: pyclipper (>=1.3.0,<2.0.0)
Requires-Dist: tqdm (>=4.64.1,<5.0.0)
